moat/__init__.py
moat/__main__.py
moat/_cfg.yaml
moat/main.py
moat/lib/__init__.py
moat/pdb/__init__.py
moat/pdb/_main.py
moat/signal/__init__.py
moat/signal/api.py
moat-0.11.8.dist-info/licenses/LICENSE.txt
moat-0.11.8.dist-info/METADATA
moat-0.11.8.dist-info/WHEEL
moat-0.11.8.dist-info/entry_points.txt
moat-0.11.8.dist-info/top_level.txt
moat-0.11.8.dist-info/RECORD
