Metadata-Version: 2.4
Name: moat
Version: 0.11.8
Summary: The command line for MoaT
Author-email: Matthias Urlichs <matthias@urlichs.de>
Project-URL: homepage, https://m-o-a-t.org
Project-URL: repository, https://github.com/M-o-a-T/moat
Keywords: MoaT
Classifier: Intended Audience :: Developers
Classifier: Programming Language :: Python :: 3
Classifier: Framework :: AsyncIO
Classifier: Framework :: Trio
Classifier: Framework :: AnyIO
Classifier: Development Status :: 4 - Beta
Requires-Python: >=3.12
License-File: LICENSE.txt
Requires-Dist: anyio~=4.0
Requires-Dist: asyncscope
Requires-Dist: moat-util~=0.61.1
Requires-Dist: moat-db~=0.2.5
Requires-Dist: moat-ems-inv~=0.2.12
Requires-Dist: moat-lib-rpc~=0.4.11
Requires-Dist: moat-lib-codec~=0.4.9
Requires-Dist: moat-lib-config~=0.1.0
Requires-Dist: moat-lib-diffiehellman~=0.13.5
Requires-Dist: moat-lib-gpio~=0.9.2
Requires-Dist: moat-lib-micro~=0.1.0
Requires-Dist: moat-lib-pid~=0.6.6
Requires-Dist: moat-lib-priomap~=0.2.2
Requires-Dist: moat-lib-proxy~=0.1.0
Requires-Dist: moat-lib-ring~=0.2.1
Requires-Dist: moat-lib-run~=0.1.0
Requires-Dist: moat-link~=0.2.44
Requires-Dist: moat-link-server~=0.3.24
Requires-Dist: moat-micro~=0.17.10
Dynamic: license-file
